v4l2py/__init__.py
v4l2py/device.py
v4l2py/io.py
v4l2py/raw.py
v4l2py-3.0.0.dist-info/LICENSE
v4l2py-3.0.0.dist-info/METADATA
v4l2py-3.0.0.dist-info/WHEEL
v4l2py-3.0.0.dist-info/top_level.txt
v4l2py-3.0.0.dist-info/RECORD
