Metadata-Version: 2.1
Name: v4l2py
Version: 3.0.0
Summary: Human friendly video for linux
Author-email: Jose Tiago Macara Coutinho <coutinhotiago@gmail.com>
License: GPL-3.0-or-later
Project-URL: Documentation, https://github.com/tiagocoutinho/v4l2py
Project-URL: Homepage, https://github.com/tiagocoutinho/v4l2py
Project-URL: Source, https://github.com/tiagocoutinho/v4l2py
Classifier: Development Status :: 4 - Beta
Classifier: Intended Audience :: Developers
Classifier: Intended Audience :: System Administrators
Classifier: License :: OSI Approved :: GNU General Public License v3 (GPLv3)
Classifier: Operating System :: POSIX :: Linux
Classifier: Programming Language :: Python :: 3
Classifier: Programming Language :: Python :: 3.9
Classifier: Programming Language :: Python :: 3.10
Classifier: Programming Language :: Python :: 3.11
Classifier: Programming Language :: Python :: 3.12
Classifier: Topic :: Multimedia :: Video
Classifier: Topic :: Multimedia :: Video :: Capture
Requires-Python: >=3.9
License-File: LICENSE
Requires-Dist: linuxpy >=0.9.0
Provides-Extra: build
Requires-Dist: build >=0.10.0 ; extra == 'build'
Requires-Dist: twine >=4.0.2 ; extra == 'build'
Provides-Extra: dev
Requires-Dist: black >=23.3.0 ; extra == 'dev'
Requires-Dist: build >=0.10.0 ; extra == 'dev'
Requires-Dist: ruff >=0.0.261 ; extra == 'dev'
Requires-Dist: twine >=4.0.2 ; extra == 'dev'
Requires-Dist: ward >=0.67.0b0 ; extra == 'dev'
Requires-Dist: ward-coverage >=0.3.0 ; extra == 'dev'
Provides-Extra: test
Requires-Dist: ward >=0.67.0b0 ; extra == 'test'
Requires-Dist: ward-coverage >=0.3.0 ; extra == 'test'
